[{"title":"Promotion in Moscow, Russia.","date":"","description":"","body":"We did our Japanese cut flower promotion in Moscow, Russia in January 2022. Russia is the biggest destination of Japanese cut flowers from JPEC in 2021. We shipped Prunus, Spiraea, Lindera, Ranunculus, Lisianthus, Lathyrus, Epidendrum, Cymbidium. Our partner in Moscow made display at their Cash and Carry place, also they give flowers to the customers (Designers, Florists, Floral school eachers, Instagramers). We can confirm many nice activities by our partner and customers in Instagram with #japanflower. We had good experience with Russian customers, and we hope it makes more and more customers in Russia who can enjoy our Japanese flowers!\n","ref":"/en/news/20220215/"},{"title":"2020 result","date":"","description":"","body":"not ready\n","ref":"/en/news/20210624/"},{"title":"Eco-pochi workshop 2017 in Hong Kong","date":"","description":"","body":"              Back to the list ","ref":"/en/galleries/eco-pochi-workshop-2017-in-hong-kong/"},{"title":"Farm visiting for oversea buyers 2017 February","date":"","description":"","body":"                                 Back to the list ","ref":"/en/galleries/farm-visiting-for-oversea-buyers-2017-february/"},{"title":"JPEC Flower Show 2017 in Dubai","date":"","description":"","body":"                                     Back to the list ","ref":"/en/galleries/jpec-flower-show-2017-in-dubai/"},{"title":"JPEC Flower Show 2017 in Saudi Arabia","date":"","description":"","body":"                    Back to the list ","ref":"/en/galleries/jpec-flower-show-2017-in-saudi-arabia/"},{"title":"Farm visiting for oversea buyers 2016 September","date":"","description":"","body":"                    Back to the list ","ref":"/en/galleries/farm-visiting-for-oversea-buyers-2016-september/"},{"title":"Flower Expo 2016 Moscow","date":"","description":"","body":"                  Back to the list ","ref":"/en/galleries/flower-expo-2016-moscow/"},{"title":"IFTF 2016","date":"","description":"","body":"                 Back to the list ","ref":"/en/galleries/iftf-2016/"},{"title":"JPEC Flower Show 2012 in Hong Kong","date":"","description":"","body":"                                Back to the list ","ref":"/en/galleries/jpec-flower-show-2012-in-hong-kong/"},{"title":"JPEC Flower Show 2013 in Hong Kong","date":"","description":"","body":"                                                       Back to the list ","ref":"/en/galleries/jpec-flower-show-2013-in-hong-kong/"},{"title":"JPEC Flower Show 2016 in Australia","date":"","description":"","body":"                   Back to the list ","ref":"/en/galleries/jpec-flower-showcase-2016-in-australia/"},{"title":"JPEC Flower Show 2016 in Hong Kong","date":"","description":"","body":"                                                                    Back to the list ","ref":"/en/galleries/jpec-flower-show-2016-in-hong-kong/"},{"title":"JPEC Flower Show 2016 in Philippine","date":"","description":"","body":"                              Back to the list ","ref":"/en/galleries/jpec-flower-show-2016-in-philippine/"},{"title":"JPEC Store promotion 2016 in Hong Kong","date":"","description":"","body":"                                   Back to the list ","ref":"/en/galleries/jpec-store-promotion-2016-in-hong-kong/"},{"title":"Seminer 2016","date":"","description":"","body":"       Back to the list ","ref":"/en/galleries/seminer-2016/"},{"title":"semminer","date":"","description":"","body":"      Back to the list ","ref":"/en/galleries/semminer/"},{"title":"JPEC Workshop 2014 spring Hong Kong","date":"","description":"","body":"                 Back to the list ","ref":"/en/galleries/jpec-workshop-2014-spring-hong-kong/"},{"title":"JPEC ワークショップ 2014冬 IN 香港","date":"","description":"","body":"                                Back to the list ","ref":"/en/galleries/jpec-workshop-2014-winter-hong-kong/"},{"title":"IPM Dubai 2013","date":"","description":"","body":"            Back to the list ","ref":"/en/galleries/ipm-dubai-2013/"},{"title":"JPEC Store promotion 2013-2014","date":"","description":"","body":"                       Back to the list ","ref":"/en/galleries/jpec-store-promotion-2013-2014/"},{"title":"JPEC Workshop 2013 autumn Hong Kong","date":"","description":"","body":"                Back to the list ","ref":"/en/galleries/jpec-workshop-2013-autumn-hong-kong/"},{"title":"JPEC Workshop 2012 in Hong Kong","date":"","description":"","body":"              Back to the list ","ref":"/en/galleries/jpec-workshop-2012-in-hong-kong/"},{"title":"JPEC Workshop 2012 in Singapore","date":"","description":"","body":"                                             Back to the list ","ref":"/en/galleries/jpec-workshop-2012-in-singapore/"},{"title":"JPEC Workshop 2012 Winter","date":"","description":"","body":"             Back to the list ","ref":"/en/galleries/jpec-workshop-2012-winter/"},{"title":"Contact","date":"","description":"","body":"","ref":"/en/contact/"}]